MANIFEST.in
README.txt
setup.py
pycoap/__init__.py
pycoap/block1.py
pycoap/block2.py
pycoap/buffer.py
pycoap/client.py
pycoap/constants.py
pycoap/exceptions.py
pycoap/layer.py
pycoap/observe.py
pycoap/request.py
pycoap/response.py
pycoap/xmitter.py
pycoap.egg-info/PKG-INFO
pycoap.egg-info/SOURCES.txt
pycoap.egg-info/dependency_links.txt
pycoap.egg-info/top_level.txt
pycoap/packet/code.py
pycoap/packet/messageID.py
pycoap/packet/messageType.py
pycoap/packet/options.py
pycoap/packet/packet.py
pycoap/packet/payload.py
pycoap/packet/token.py