Metadata-Version: 1.1
Name: pycoap
Version: 0.0.7
Summary: UNKNOWN
Home-page: https://bitbucket.org/ericwilkison/pycoap
Author: Eric Wilkison
Author-email: ericw@wilkison.com
License: MIT License
Platform: UNKNOWN
Classifier: Programming Language :: Python :: 3
Classifier: License :: OSI Approved :: MIT License
Classifier: Operating System :: OS Independent
